reactivated/__init__.py
reactivated/admin.py
reactivated/apps.py
reactivated/backend.py
reactivated/checks.py
reactivated/constraints.py
reactivated/fields.py
reactivated/forms.py
reactivated/middleware.py
reactivated/models.py
reactivated/pick.py
reactivated/plugin.py
reactivated/py.typed
reactivated/renderer.py
reactivated/rpc.py
reactivated/stubs.py
reactivated/templates.py
reactivated/types.py
reactivated/utils.py
reactivated/views.py
reactivated/widgets.py
reactivated/management/__init__.py
reactivated/management/commands/__init__.py
reactivated/management/commands/build.py
reactivated/management/commands/generate_client_assets.py
reactivated/management/commands/print_schema.py
reactivated/migrations/__init__.py
reactivated/serialization/__init__.py
reactivated/serialization/builtins.py
reactivated/serialization/context_processors.py
reactivated/serialization/registry.py
reactivated/serialization/widgets.py
reactivated/templates/reactivated/autocomplete
reactivated/templates/reactivated/interface.html
"reactivated-0.48.0.data/data/""""/package.json"
sample/__init__.py
sample/manage.py
sample/server/__init__.py
sample/server/forms.py
sample/server/settings.py
sample/server/urls.py
sample/server/wsgi.py
sample/server/apps/__init__.py
sample/server/apps/samples/__init__.py
sample/server/apps/samples/admin.py
sample/server/apps/samples/apps.py
sample/server/apps/samples/forms.py
sample/server/apps/samples/interfaces.py
sample/server/apps/samples/models.py
sample/server/apps/samples/templates.py
sample/server/apps/samples/tests.py
sample/server/apps/samples/views.py
sample/server/apps/samples/migrations/0001_initial.py
sample/server/apps/samples/migrations/0002_opera_uuid.py
sample/server/apps/samples/migrations/__init__.py
tests/__init__.py
tests/autocomplete.py
tests/conftest.py
tests/e2e.py
tests/exports.py
tests/fields.py
tests/forms.py
tests/renderer.py
tests/rpc.py
tests/serialization.py
tests/templates.py
tests/types.py
tests/urls.py
tests/views.py
reactivated-0.48.0.dist-info/LICENSE
reactivated-0.48.0.dist-info/METADATA
reactivated-0.48.0.dist-info/WHEEL
reactivated-0.48.0.dist-info/top_level.txt
reactivated-0.48.0.dist-info/RECORD
