Metadata-Version: 2.1
Name: reactivated
Version: 0.48.0
Summary: A statically typed framework to create Django sites with a React frontend.
Home-page: https://github.com/silviogutierrez/django-react
Author: Silvio Gutierrez
Author-email: silviogutierrez@gmail.com
Classifier: Programming Language :: Python :: 3
Classifier: License :: OSI Approved :: MIT License
Classifier: Operating System :: OS Independent
License-File: LICENSE
Requires-Dist: requests>=2.25.0
Requires-Dist: requests-unixsocket2>=0.4.0
Requires-Dist: mypy~=1.14
Requires-Dist: django-stubs~=5.1
Requires-Dist: simplejson>=3.16.0
